{
  "id": "ni-boknoy-ken-ni-tikboy-9786214733392",
  "title": "Ni Boknoy Ken ni Tikboy",
  "author": "Myrna S. Diaz",
  "publisher": "Shirley Publishing House",
  "type": "Children's Book",
  "year": 2025,
  "publicationDate": "April 2, 2025",
  "edition": "Unang edisyon",
  "language": "Iloko",
  "format": "Softbound/Paperback",
  "category": "Children's book",
  "identifierLabel": "ISBN",
  "identifier": "978-621-473-339-2",
  "cover": "assets/covers/9786214733392-ni-boknoy-ken-ni-tikboy.webp",
  "abstract": "",
  "keywords": [
    "boknoy",
    "tikboy",
    "children's book",
    "iloko"
  ],
  "accessUrl": "contact.html",
  "accessLabel": "Inquire About This Publication",
  "featured": false,
  "subjectCategory": "Children's Literature & Storybooks"
}