{
  "id": "strategic-intervention-material-in-araling-panlipunan-6-9786214732135",
  "title": "Strategic Intervention Material in araling Panlipunan 6",
  "author": "Rolando M. Ladia",
  "publisher": "Shirley Publishing House",
  "type": "Textbook / Educational Material",
  "year": 2024,
  "publicationDate": "February 28, 2024",
  "edition": "UNANG EDISYON",
  "language": "FILIPINO",
  "format": "Softbound/Paperback",
  "category": "Textbook / educational materials",
  "identifierLabel": "ISBN",
  "identifier": "978-621-473-213-5",
  "cover": "assets/covers/9786214732135-strategic-intervention-material-in-araling-pa.webp",
  "abstract": "",
  "keywords": [
    "strategic",
    "intervention",
    "material",
    "araling",
    "panlipunan",
    "textbook / educational material",
    "textbook / educational materials",
    "filipino"
  ],
  "accessUrl": "contact.html",
  "accessLabel": "Inquire About This Publication",
  "featured": false,
  "subjectCategory": "Social Studies, Culture & Indigenous Knowledge"
}